Metadata-Version: 2.1
Name: pwdsphinx
Version: 2.0.1
Summary: SPHINX password protocol
Home-page: https://github.com/stef/pwdsphinx
Author: Stefan Marsiske
Author-email: sphinx@ctrlc.hu
License: GPLv3
Classifier: Development Status :: 4 - Beta
Classifier: License :: OSI Approved :: GNU General Public License v3 or later (GPLv3+)
Classifier: Topic :: Security :: Cryptography
Classifier: Topic :: Security
License-File: LICENSE
Requires-Dist: pysodium
Requires-Dist: SecureString
Requires-Dist: qrcodegen
Requires-Dist: zxcvbn-python
Requires-Dist: pyequihash
Requires-Dist: pyoprf>=0.6.0
